torchsat/__init__.py
torchsat/datasets/__init__.py
torchsat/datasets/eurosat.py
torchsat/datasets/folder.py
torchsat/datasets/nwpu_resisc45.py
torchsat/datasets/patternnet.py
torchsat/datasets/sat.py
torchsat/datasets/utils.py
torchsat/models/__init__.py
torchsat/models/utils.py
torchsat/models/classification/__init__.py
torchsat/models/classification/densenet.py
torchsat/models/classification/inception.py
torchsat/models/classification/mobilenet.py
torchsat/models/classification/resnet.py
torchsat/models/classification/vgg.py
torchsat/models/segmentation/__init__.py
torchsat/models/segmentation/unet.py
torchsat/transforms/__init__.py
torchsat/transforms/functional.py
torchsat/transforms/transforms_cls.py
torchsat/transforms/transforms_det.py
torchsat/transforms/transforms_seg.py
torchsat/utils/__init__.py
torchsat/utils/visualizer.py
torchsat-0.0.1.dist-info/LICENSE
torchsat-0.0.1.dist-info/METADATA
torchsat-0.0.1.dist-info/WHEEL
torchsat-0.0.1.dist-info/top_level.txt
torchsat-0.0.1.dist-info/RECORD
