Metadata-Version: 2.1
Name: torchsat
Version: 0.0.1
Summary: TorchSat is an open-source PyTorch framework for satellite imagery analysis.
Home-page: https://github.com/sshuair/torchsat
Author: sshuair
Author-email: sshuair@gmail.com
License: MIT
Keywords: pytorch deep learning satellite remote sensing
Platform: UNKNOWN
Requires-Dist: numpy (>=1.13.0)
Requires-Dist: scipy (>=1.1.0)
Requires-Dist: pillow (>=5.0.0)
Requires-Dist: six (>=1.11.0)
Requires-Dist: tifffile (>=2019.1.1)
Requires-Dist: opencv-python (>=3.2.0.6)
Requires-Dist: torch (>=1.0.0)
Requires-Dist: torchvision (>=0.2.0)
